gce_api-3.0.0.dist-info/DESCRIPTION.rst
gce_api-3.0.0.dist-info/METADATA
gce_api-3.0.0.dist-info/RECORD
gce_api-3.0.0.dist-info/WHEEL
gce_api-3.0.0.dist-info/entry_points.txt
gce_api-3.0.0.dist-info/metadata.json
gce_api-3.0.0.dist-info/pbr.json
gce_api-3.0.0.dist-info/top_level.txt
gceapi/__init__.py
gceapi/auth.py
gceapi/config.py
gceapi/context.py
gceapi/exception.py
gceapi/i18n.py
gceapi/opts.py
gceapi/paths.py
gceapi/service.py
gceapi/version.py
gceapi/wsgi.py
gceapi/wsgi_ext.py
gceapi/api/__init__.py
gceapi/api/address_api.py
gceapi/api/address_neutron_api.py
gceapi/api/address_nova_api.py
gceapi/api/addresses.py
gceapi/api/base_api.py
gceapi/api/clients.py
gceapi/api/common.py
gceapi/api/discovery.py
gceapi/api/disk_api.py
gceapi/api/disks.py
gceapi/api/firewall_api.py
gceapi/api/firewalls.py
gceapi/api/image_api.py
gceapi/api/images.py
gceapi/api/instance_address_api.py
gceapi/api/instance_api.py
gceapi/api/instance_disk_api.py
gceapi/api/instances.py
gceapi/api/machine_type_api.py
gceapi/api/machine_types.py
gceapi/api/network_api.py
gceapi/api/network_neutron_api.py
gceapi/api/network_nova_api.py
gceapi/api/networks.py
gceapi/api/oauth.py
gceapi/api/operation_api.py
gceapi/api/operation_util.py
gceapi/api/operations.py
gceapi/api/opts.py
gceapi/api/project_api.py
gceapi/api/projects.py
gceapi/api/region_api.py
gceapi/api/regions.py
gceapi/api/route_api.py
gceapi/api/route_neutron_api.py
gceapi/api/route_nova_api.py
gceapi/api/routes.py
gceapi/api/scopes.py
gceapi/api/snapshot_api.py
gceapi/api/snapshots.py
gceapi/api/utils.py
gceapi/api/wsgi.py
gceapi/api/zone_api.py
gceapi/api/zones.py
gceapi/cmd/__init__.py
gceapi/cmd/api.py
gceapi/cmd/manage.py
gceapi/db/__init__.py
gceapi/db/api.py
gceapi/db/migration.py
gceapi/db/sqlalchemy/__init__.py
gceapi/db/sqlalchemy/api.py
gceapi/db/sqlalchemy/migration.py
gceapi/db/sqlalchemy/models.py
gceapi/db/sqlalchemy/migrate_repo/README
gceapi/db/sqlalchemy/migrate_repo/__init__.py
gceapi/db/sqlalchemy/migrate_repo/manage.py
gceapi/db/sqlalchemy/migrate_repo/migrate.cfg
gceapi/db/sqlalchemy/migrate_repo/versions/001_icehouse.py
gceapi/db/sqlalchemy/migrate_repo/versions/__init__.py
gceapi/tests/__init__.py
