Metadata-Version: 2.0
Name: gce-api
Version: 3.0.0
Summary: OpenStack Gceapi Service
Home-page: https://launchpad.net/gce-api
Author: OpenStack
Author-email: openstack-dev@lists.openstack.org
License: Apache License, Version 2.0
Platform: UNKNOWN
Classifier: Environment :: OpenStack
Classifier: Intended Audience :: Information Technology
Classifier: Intended Audience :: System Administrators
Classifier: License :: OSI Approved :: Apache Software License
Classifier: Operating System :: POSIX :: Linux
Classifier: Programming Language :: Python
Requires-Dist: Babel (>=2.3.4)
Requires-Dist: eventlet (!=0.18.3,>=0.18.2)
Requires-Dist: greenlet (>=0.3.2)
Requires-Dist: oslo.config (>=3.14.0)
Requires-Dist: oslo.concurrency (>=3.8.0)
Requires-Dist: oslo.context (>=2.9.0)
Requires-Dist: oslo.db (>=4.10.0,!=4.13.1,!=4.13.2)
Requires-Dist: oslo.log (>=3.11.0)
Requires-Dist: oslo.utils (>=3.16.0)
Requires-Dist: oslo.serialization (>=1.10.0)
Requires-Dist: oslo.service (>=1.10.0)
Requires-Dist: paramiko (>=2.0)
Requires-Dist: Paste
Requires-Dist: PasteDeploy (>=1.5.0)
Requires-Dist: pbr (>=1.6)
Requires-Dist: python-cinderclient (!=1.7.0,>=1.6.0,!=1.7.1)
Requires-Dist: python-glanceclient (>=2.5.0)
Requires-Dist: python-keystoneclient (!=2.1.0,>=2.0.0)
Requires-Dist: python-neutronclient (>=5.1.0)
Requires-Dist: python-novaclient (>=2.29.0,!=2.33.0)
Requires-Dist: six (>=1.9.0)
Requires-Dist: SQLAlchemy (>=1.0.10,<1.1.0)
Requires-Dist: sqlalchemy-migrate (>=0.9.6)
Requires-Dist: WebOb (>=1.2.3)
Requires-Dist: Routes (>=1.12.3,!=2.0,!=2.3.0); (python_version!='2.7')
Requires-Dist: Routes (!=2.1,>=1.12.3,!=2.0,!=2.3.0); (python_version=='2.7')
